README
bayfiles.py
setup.py
bayfiles.egg-info/PKG-INFO
bayfiles.egg-info/SOURCES.txt
bayfiles.egg-info/dependency_links.txt
bayfiles.egg-info/requires.txt
bayfiles.egg-info/top_level.txt
src/Account.py
src/File.py
src/__init__.py